setup.cfg
setup.py
hggit2/hggitRun.py
hggit2.egg-info/PKG-INFO
hggit2.egg-info/SOURCES.txt
hggit2.egg-info/dependency_links.txt
hggit2.egg-info/top_level.txt