Metadata-Version: 1.0
Name: hggit2
Version: 0.1
Summary: It will install hg-git plugin alongiwth all the required dependencies. Also, since hg-git is implemented in Python2, it will ask the user, do you want it to make Python3 compatible or not?
Home-page: https://bitbucket.org/vishav_FSU/fsu_mercurial/branch/default
Author: Vishav Pandhi, Jorge Gonzalez
Author-email: vishavpandhi@gmail.com, jrg13h@my.fsu.edu
License: UNKNOWN
Keywords: installing,testing
Platform: UNKNOWN
